CHANGELOG
LICENSE
MANIFEST.in
WAIVER
WAIVER.asc
requirements.txt
setup.cfg
setup.py
test_requirements.txt
eth_badgetoken/__init__.py
eth_badgetoken/token.py
eth_badgetoken/data/.chainlib
eth_badgetoken/data/BadgeToken.bin
eth_badgetoken/data/BadgeToken.json
eth_badgetoken/data/BadgeToken.metadata.json
eth_badgetoken/runnable/deploy.py
eth_badgetoken/runnable/mint.py
eth_badgetoken/unittest/__init__.py
eth_badgetoken/unittest/base.py
eth_badgetoken/unittest/interface.py
eth_erc721/__init__.py
eth_erc721/erc721.py
eth_erc721.egg-info/PKG-INFO
eth_erc721.egg-info/SOURCES.txt
eth_erc721.egg-info/dependency_links.txt
eth_erc721.egg-info/entry_points.txt
eth_erc721.egg-info/requires.txt
eth_erc721.egg-info/top_level.txt
eth_erc721/runnable/transfer.py
eth_erc721/unittest/__init__.py
eth_erc721/unittest/base.py
eth_erc721/unittest/enum.py
tests/test_app.py