Metadata-Version: 2.1
Name: eth-erc721
Version: 0.2.0
Summary: ERC721 interface and simple contract with deployment script providing arbitrary minting of NFTs with freely settable tokenids
Home-page: https://git.defalsify.org/eth-erc721
Author: Louis Holbrook
Author-email: dev@holbrook.no
License: AGPLv3+
Keywords: dlt,blockchain,cryptocurrency,ethereum,token,nft
Classifier: Programming Language :: Python :: 3
Classifier: Operating System :: OS Independent
Classifier: Development Status :: 4 - Beta
Classifier: Environment :: Console
Classifier: Intended Audience :: Developers
Classifier: License :: OSI Approved :: GNU Affero General Public License v3 or later (AGPLv3+)
Classifier: Topic :: Internet
Classifier: Topic :: Software Development :: Libraries
Requires-Python: >=3.8
License-File: LICENSE
